odoo/addons/connector_dicom/README.rst
odoo/addons/connector_dicom/__init__.py
odoo/addons/connector_dicom/__manifest__.py
odoo/addons/connector_dicom/data/ir_config_parameter.xml
odoo/addons/connector_dicom/i18n/connector_dicom.pot
odoo/addons/connector_dicom/i18n/es_CL.po
odoo/addons/connector_dicom/models/__init__.py
odoo/addons/connector_dicom/models/res_partner.py
odoo/addons/connector_dicom/models/res_partner_dicom.py
odoo/addons/connector_dicom/readme/CONFIGURE.rst
odoo/addons/connector_dicom/readme/CONTRIBUTORS.rst
odoo/addons/connector_dicom/readme/DESCRIPTION.rst
odoo/addons/connector_dicom/readme/USAGE.rst
odoo/addons/connector_dicom/security/ir.model.access.csv
odoo/addons/connector_dicom/static/description/icon.png
odoo/addons/connector_dicom/static/description/index.html
odoo/addons/connector_dicom/views/res_partner.xml
odoo/addons/connector_dicom/views/res_partner_dicom.xml
odoo12_addon_connector_dicom-12.0.1.0.2.dist-info/METADATA
odoo12_addon_connector_dicom-12.0.1.0.2.dist-info/WHEEL
odoo12_addon_connector_dicom-12.0.1.0.2.dist-info/top_level.txt
odoo12_addon_connector_dicom-12.0.1.0.2.dist-info/RECORD
